{
  "name": "scans/fwcsODXtdPzFR9d3Vd7z/M6zoVK9MTIEeo2n138WO/91ae806b8f03b5d56c5e99c7b15874e5f357d09c093df79d63375448691bcd22/screenshot.jpg",
  "bucket": "accessibilitychecker-c6585.appspot.com",
  "metageneration": 1,
  "generation": 1770924152894,
  "contentType": "image/jpeg",
  "storageClass": "STANDARD",
  "cacheControl": "public, max-age=604800",
  "downloadTokens": [],
  "etag": "i7cPu3ldo0n2/xrtOmcuD3jwGZI",
  "timeCreated": "2026-02-12T19:22:32.894Z",
  "updated": "2026-02-12T19:22:32.894Z",
  "size": 132850,
  "md5Hash": "1T6WY7eCdn9RBAuquYSwYQ==",
  "crc32c": "653300611"
}