{
  "name": "scans/fwcsODXtdPzFR9d3Vd7z/M6zoVK9MTIEeo2n138WO/c384758f9437fbfbd148e032036f38466a7d77bcb88c21cc042064735f865d62/snapshot.html",
  "bucket": "accessibilitychecker-c6585.appspot.com",
  "metageneration": 1,
  "generation": 1770924184035,
  "contentType": "text/html",
  "storageClass": "STANDARD",
  "cacheControl": "public, max-age=604800",
  "downloadTokens": [],
  "etag": "THIqPVEwYoFMf7qYDApsGzVJ4M4",
  "timeCreated": "2026-02-12T19:23:04.035Z",
  "updated": "2026-02-12T19:23:04.035Z",
  "size": 54771,
  "md5Hash": "SDNUYsLJH5RGqlure6RWIQ==",
  "crc32c": "3059058667"
}