{
  "name": "scans/40OAYKCVjeY9OFOW9fhT/v9CA3Odl2E1sDzM4xeoz/8bf9ca2b62f66bdf84f839e1212d4162be0acc0862f5b181f3fa0e5bd7cf5441/snapshot.html",
  "bucket": "accessibilitychecker-c6585.appspot.com",
  "metageneration": 1,
  "generation": 1770928585147,
  "contentType": "text/html",
  "storageClass": "STANDARD",
  "cacheControl": "public, max-age=604800",
  "downloadTokens": [],
  "etag": "pZKXRdOcvrRUI8bc9QfAWqCWtx4",
  "timeCreated": "2026-02-12T20:36:25.148Z",
  "updated": "2026-02-12T20:36:25.148Z",
  "size": 100742,
  "md5Hash": "3HKFK/a4NUXI4EEZXjeWgA==",
  "crc32c": "167227955"
}