{
  "name": "scans/fwcsODXtdPzFR9d3Vd7z/4NYicrlvjIXVxuuiMNQK/c35158b4c9fef012d3d32a4ca8179829b97fa0caaf90c9e021127838490c9f79/snapshot.html",
  "bucket": "accessibilitychecker-c6585.appspot.com",
  "metageneration": 1,
  "generation": 1770917494248,
  "contentType": "text/html",
  "storageClass": "STANDARD",
  "cacheControl": "public, max-age=604800",
  "downloadTokens": [],
  "etag": "eWycIyQvPyEBVMCC+y7j5uwHS90",
  "timeCreated": "2026-02-12T17:31:34.248Z",
  "updated": "2026-02-12T17:31:34.248Z",
  "size": 30440,
  "md5Hash": "1jKpBtnbyeGVuJU20t3cHA==",
  "crc32c": "3847822989"
}