{
  "name": "scans/fwcsODXtdPzFR9d3Vd7z/4NYicrlvjIXVxuuiMNQK/c384758f9437fbfbd148e032036f38466a7d77bcb88c21cc042064735f865d62/snapshot.html",
  "bucket": "accessibilitychecker-c6585.appspot.com",
  "metageneration": 1,
  "generation": 1770917495667,
  "contentType": "text/html",
  "storageClass": "STANDARD",
  "cacheControl": "public, max-age=604800",
  "downloadTokens": [],
  "etag": "5fSJJVA77nQ4gkeUyzncFFKpfxQ",
  "timeCreated": "2026-02-12T17:31:35.667Z",
  "updated": "2026-02-12T17:31:35.667Z",
  "size": 54771,
  "md5Hash": "uDyCwBGcq65txmLJ+ay/Eg==",
  "crc32c": "1762845033"
}